scirisweb/__init__.py
scirisweb/sw_app.py
scirisweb/sw_config.py
scirisweb/sw_datastore.py
scirisweb/sw_rpcs.py
scirisweb/sw_server.py
scirisweb/sw_tasks.py
scirisweb/sw_users.py
scirisweb/sw_version.py
scirisweb-1.0.1.dist-info/LICENSE
scirisweb-1.0.1.dist-info/METADATA
scirisweb-1.0.1.dist-info/WHEEL
scirisweb-1.0.1.dist-info/top_level.txt
scirisweb-1.0.1.dist-info/RECORD
