Metadata-Version: 2.1
Name: scirisweb
Version: 1.0.1
Summary: Scientific webapps for Python
Home-page: http://github.com/sciris/scirisweb
Author: Sciris Development Team
Author-email: info@sciris.org
Keywords: scientific,webapp,framework
Platform: OS Independent
Classifier: Development Status :: 5 - Production/Stable
Classifier: Intended Audience :: Science/Research
Classifier: License :: OSI Approved :: MIT License
Classifier: Operating System :: OS Independent
Classifier: Programming Language :: Python
Classifier: Programming Language :: Python :: 3
Classifier: Programming Language :: Python :: 3.8
Classifier: Programming Language :: Python :: 3.9
Classifier: Programming Language :: Python :: 3.10
Classifier: Programming Language :: Python :: 3.11
Classifier: Programming Language :: Python :: 3.12
Classifier: Topic :: Software Development
Classifier: Topic :: Scientific/Engineering
License-File: LICENSE
Requires-Dist: sciris
Requires-Dist: decorator
Requires-Dist: redis
Requires-Dist: mpld3
Requires-Dist: werkzeug
Requires-Dist: flask
Requires-Dist: flask-login
Requires-Dist: flask-session
Requires-Dist: flask-cors
Requires-Dist: celery
Requires-Dist: twisted
Requires-Dist: service-identity
Requires-Dist: pyasn1
Requires-Dist: pyparsing
Requires-Dist: sqlalchemy
